{"config":{"output_file":null,"full_docs":false,"pub_only":false,"reachable_only":false,"distro_crate":false,"signatures":false,"borrow_data":false},"version":"0.19.0","compilation":{"directory":"/home/farjad-ali/Rust/Quarter 2/embedded_rust/14-i2c","program":"/home/farjad-ali/.rustup/toolchains/stable-x86_64-unknown-linux-gnu/bin/rls","arguments":[],"output":"/home/farjad-ali/Rust/Quarter 2/embedded_rust/14-i2c/target/rls/thumbv7em-none-eabihf/debug/deps/libi2c-f1249dd62c8ebe82.rmeta"},"prelude":{"crate_id":{"name":"i2c","disambiguator":[9707061598673915484,8370488930474990337]},"crate_root":"src","external_crates":[{"file_name":"/home/farjad-ali/Rust/Quarter 2/embedded_rust/14-i2c/src/main.rs","num":1,"id":{"name":"core","disambiguator":[16410780912699979615,14786055825151821009]}},{"file_name":"/home/farjad-ali/Rust/Quarter 2/embedded_rust/14-i2c/src/main.rs","num":2,"id":{"name":"compiler_builtins","disambiguator":[16250002860209205769,6607268543709446693]}},{"file_name":"/home/farjad-ali/Rust/Quarter 2/embedded_rust/14-i2c/src/main.rs","num":3,"id":{"name":"rustc_std_workspace_core","disambiguator":[14103481253267247487,17467155086432962609]}},{"file_name":"/home/farjad-ali/Rust/Quarter 2/embedded_rust/14-i2c/src/main.rs","num":4,"id":{"name":"aux14","disambiguator":[12477298180272559557,6274968422279098803]}},{"file_name":"/home/farjad-ali/Rust/Quarter 2/embedded_rust/14-i2c/src/main.rs","num":5,"id":{"name":"panic_itm","disambiguator":[1402773219691913190,17204708562610434376]}},{"file_name":"/home/farjad-ali/Rust/Quarter 2/embedded_rust/14-i2c/src/main.rs","num":6,"id":{"name":"cortex_m","disambiguator":[9514762271344919434,18443122035310791560]}},{"file_name":"/home/farjad-ali/Rust/Quarter 2/embedded_rust/14-i2c/src/main.rs","num":7,"id":{"name":"aligned","disambiguator":[302692839918583035,9603114729353535693]}},{"file_name":"/home/farjad-ali/Rust/Quarter 2/embedded_rust/14-i2c/src/main.rs","num":8,"id":{"name":"as_slice","disambiguator":[11716226698236209174,15510150420740182695]}},{"file_name":"/home/farjad-ali/Rust/Quarter 2/embedded_rust/14-i2c/src/main.rs","num":9,"id":{"name":"generic_array","disambiguator":[16676433861474099338,2165757215028005619]}},{"file_name":"/home/farjad-ali/Rust/Quarter 2/embedded_rust/14-i2c/src/main.rs","num":10,"id":{"name":"typenum","disambiguator":[5527154902614117398,2488479521681713790]}},{"file_name":"/home/farjad-ali/Rust/Quarter 2/embedded_rust/14-i2c/src/main.rs","num":11,"id":{"name":"generic_array","disambiguator":[10616777522099223402,12595951863927918193]}},{"file_name":"/home/farjad-ali/Rust/Quarter 2/embedded_rust/14-i2c/src/main.rs","num":12,"id":{"name":"stable_deref_trait","disambiguator":[238294044864312315,18385378109712252382]}},{"file_name":"/home/farjad-ali/Rust/Quarter 2/embedded_rust/14-i2c/src/main.rs","num":13,"id":{"name":"bare_metal","disambiguator":[15906446097264242337,1430246926477955391]}},{"file_name":"/home/farjad-ali/Rust/Quarter 2/embedded_rust/14-i2c/src/main.rs","num":14,"id":{"name":"volatile_register","disambiguator":[7316347500988490996,7091506433184964599]}},{"file_name":"/home/farjad-ali/Rust/Quarter 2/embedded_rust/14-i2c/src/main.rs","num":15,"id":{"name":"vcell","disambiguator":[4461580152574820271,5655097032806465878]}},{"file_name":"/home/farjad-ali/Rust/Quarter 2/embedded_rust/14-i2c/src/main.rs","num":16,"id":{"name":"cortex_m_rt","disambiguator":[18243088186130340819,17015650215914363966]}},{"file_name":"/home/farjad-ali/Rust/Quarter 2/embedded_rust/14-i2c/src/main.rs","num":17,"id":{"name":"cortex_m_rt_macros","disambiguator":[259780975637706482,9247701130211580840]}},{"file_name":"/home/farjad-ali/Rust/Quarter 2/embedded_rust/14-i2c/src/main.rs","num":18,"id":{"name":"r0","disambiguator":[2235721308740287632,5161421979057078425]}},{"file_name":"/home/farjad-ali/Rust/Quarter 2/embedded_rust/14-i2c/src/main.rs","num":19,"id":{"name":"f3","disambiguator":[7028467842590276270,994478779748295365]}},{"file_name":"/home/farjad-ali/Rust/Quarter 2/embedded_rust/14-i2c/src/main.rs","num":20,"id":{"name":"l3gd20","disambiguator":[6147648548684893978,8335918483122893409]}},{"file_name":"/home/farjad-ali/Rust/Quarter 2/embedded_rust/14-i2c/src/main.rs","num":21,"id":{"name":"embedded_hal","disambiguator":[7534267860175315775,14347467878867631697]}},{"file_name":"/home/farjad-ali/Rust/Quarter 2/embedded_rust/14-i2c/src/main.rs","num":22,"id":{"name":"nb","disambiguator":[7383591593874541404,15345207942558291554]}},{"file_name":"/home/farjad-ali/Rust/Quarter 2/embedded_rust/14-i2c/src/main.rs","num":23,"id":{"name":"nb","disambiguator":[8767143876972068785,9448938617414446237]}},{"file_name":"/home/farjad-ali/Rust/Quarter 2/embedded_rust/14-i2c/src/main.rs","num":24,"id":{"name":"void","disambiguator":[16165431980142412228,1786522028750869639]}},{"file_name":"/home/farjad-ali/Rust/Quarter 2/embedded_rust/14-i2c/src/main.rs","num":25,"id":{"name":"generic_array","disambiguator":[15865479132967547676,8822653941127134475]}},{"file_name":"/home/farjad-ali/Rust/Quarter 2/embedded_rust/14-i2c/src/main.rs","num":26,"id":{"name":"lsm303dlhc","disambiguator":[4492744471595041585,9627995605999401124]}},{"file_name":"/home/farjad-ali/Rust/Quarter 2/embedded_rust/14-i2c/src/main.rs","num":27,"id":{"name":"cast","disambiguator":[1250104512197958205,12340295062318500012]}},{"file_name":"/home/farjad-ali/Rust/Quarter 2/embedded_rust/14-i2c/src/main.rs","num":28,"id":{"name":"stm32f30x_hal","disambiguator":[6045049041123450961,16568925887310774558]}},{"file_name":"/home/farjad-ali/Rust/Quarter 2/embedded_rust/14-i2c/src/main.rs","num":29,"id":{"name":"cortex_m","disambiguator":[9532528330650127715,4017533405394099591]}},{"file_name":"/home/farjad-ali/Rust/Quarter 2/embedded_rust/14-i2c/src/main.rs","num":30,"id":{"name":"aligned","disambiguator":[16783429957430995677,4020341015745623550]}},{"file_name":"/home/farjad-ali/Rust/Quarter 2/embedded_rust/14-i2c/src/main.rs","num":31,"id":{"name":"stm32f30x","disambiguator":[3489391835419294623,6902896136568819155]}}],"span":{"file_name":"src/main.rs","byte_start":0,"byte_end":2271,"line_start":1,"line_end":75,"column_start":1,"column_end":2}},"imports":[{"kind":"Use","ref_id":{"krate":17,"index":24},"span":{"file_name":"src/main.rs","byte_start":83,"byte_end":88,"line_start":6,"line_end":6,"column_start":13,"column_end":18},"alias_span":null,"name":"entry","value":"","parent":{"krate":0,"index":0}},{"kind":"Use","ref_id":{"krate":6,"index":8},"span":{"file_name":"src/main.rs","byte_start":90,"byte_end":96,"line_start":6,"line_end":6,"column_start":20,"column_end":26},"alias_span":null,"name":"iprint","value":"","parent":{"krate":0,"index":0}},{"kind":"Use","ref_id":{"krate":6,"index":9},"span":{"file_name":"src/main.rs","byte_start":98,"byte_end":106,"line_start":6,"line_end":6,"column_start":28,"column_end":36},"alias_span":null,"name":"iprintln","value":"","parent":{"krate":0,"index":0}},{"kind":"GlobUse","ref_id":null,"span":{"file_name":"src/main.rs","byte_start":117,"byte_end":118,"line_start":6,"line_end":6,"column_start":47,"column_end":48},"alias_span":null,"name":"*","value":"_embedded_hal_timer_CountDown, _embedded_hal_serial_Read, _embedded_hal_blocking_i2c_Write, _embedded_hal_blocking_delay_DelayMs, _embedded_hal_serial_Write, _embedded_hal_blocking_spi_Write, _embedded_hal_spi_FullDuplex, _embedded_hal_blocking_i2c_Read","parent":{"krate":0,"index":0}}],"defs":[{"kind":"Mod","id":{"krate":0,"index":0},"span":{"file_name":"src/main.rs","byte_start":0,"byte_end":2271,"line_start":1,"line_end":75,"column_start":1,"column_end":2},"name":"","qualname":"::","value":"src/main.rs","parent":null,"children":[{"krate":0,"index":1},{"krate":0,"index":2},{"krate":0,"index":3},{"krate":0,"index":4},{"krate":0,"index":9},{"krate":0,"index":10},{"krate":0,"index":11},{"krate":0,"index":12},{"krate":0,"index":13}],"decl_id":null,"docs":"","sig":null,"attributes":[{"value":"deny(unsafe_code)","span":{"file_name":"src/main.rs","byte_start":0,"byte_end":21,"line_start":1,"line_end":1,"column_start":1,"column_end":22}},{"value":"no_main","span":{"file_name":"src/main.rs","byte_start":22,"byte_end":33,"line_start":2,"line_end":2,"column_start":1,"column_end":12}},{"value":"no_std","span":{"file_name":"src/main.rs","byte_start":34,"byte_end":44,"line_start":3,"line_end":3,"column_start":1,"column_end":11}}]},{"kind":"Const","id":{"krate":0,"index":9},"span":{"file_name":"src/main.rs","byte_start":145,"byte_end":157,"line_start":9,"line_end":9,"column_start":7,"column_end":19},"name":"MAGNETOMETER","qualname":"::MAGNETOMETER","value":"u8","parent":null,"children":[],"decl_id":null,"docs":"","sig":null,"attributes":[]},{"kind":"Const","id":{"krate":0,"index":10},"span":{"file_name":"src/main.rs","byte_start":228,"byte_end":237,"line_start":12,"line_end":12,"column_start":7,"column_end":16},"name":"OUT_X_H_M","qualname":"::OUT_X_H_M","value":"u8","parent":null,"children":[],"decl_id":null,"docs":"","sig":null,"attributes":[]},{"kind":"Const","id":{"krate":0,"index":11},"span":{"file_name":"src/main.rs","byte_start":256,"byte_end":265,"line_start":13,"line_end":13,"column_start":7,"column_end":16},"name":"IRA_REG_M","qualname":"::IRA_REG_M","value":"u8","parent":null,"children":[],"decl_id":null,"docs":"","sig":null,"attributes":[]},{"kind":"Local","id":{"krate":0,"index":4294967239},"span":{"file_name":"src/main.rs","byte_start":314,"byte_end":318,"line_start":17,"line_end":17,"column_start":10,"column_end":14},"name":"i2c1","qualname":"i2c1$56","value":"&stm32f30x::i2c1::RegisterBlock","parent":null,"children":[],"decl_id":null,"docs":"","sig":null,"attributes":[]},{"kind":"Local","id":{"krate":0,"index":4294967238},"span":{"file_name":"src/main.rs","byte_start":324,"byte_end":329,"line_start":17,"line_end":17,"column_start":20,"column_end":25},"name":"delay","qualname":"delay$57","value":"stm32f30x_hal::delay::Delay","parent":null,"children":[],"decl_id":null,"docs":"","sig":null,"attributes":[]},{"kind":"Local","id":{"krate":0,"index":4294967237},"span":{"file_name":"src/main.rs","byte_start":335,"byte_end":338,"line_start":17,"line_end":17,"column_start":31,"column_end":34},"name":"itm","qualname":"itm$58","value":"cortex_m::peripheral::ITM","parent":null,"children":[],"decl_id":null,"docs":"","sig":null,"attributes":[]},{"kind":"Local","id":{"krate":0,"index":4294967226},"span":{"file_name":"src/main.rs","byte_start":496,"byte_end":497,"line_start":22,"line_end":22,"column_start":25,"column_end":26},"name":"w","qualname":"$106::w","value":"&mut stm32f30x::i2c1::cr2::W","parent":null,"children":[],"decl_id":null,"docs":"","sig":null,"attributes":[]},{"kind":"Local","id":{"krate":0,"index":4294967171},"span":{"file_name":"src/main.rs","byte_start":894,"byte_end":895,"line_start":34,"line_end":34,"column_start":26,"column_end":27},"name":"w","qualname":"$134::w","value":"&mut stm32f30x::i2c1::txdr::W","parent":null,"children":[],"decl_id":null,"docs":"","sig":null,"attributes":[]},{"kind":"Local","id":{"krate":0,"index":4294967140},"span":{"file_name":"src/main.rs","byte_start":1174,"byte_end":1175,"line_start":41,"line_end":41,"column_start":29,"column_end":30},"name":"w","qualname":"$184::w","value":"&mut stm32f30x::i2c1::cr2::W","parent":null,"children":[],"decl_id":null,"docs":"","sig":null,"attributes":[]},{"kind":"Local","id":{"krate":0,"index":4294967108},"span":{"file_name":"src/main.rs","byte_start":1341,"byte_end":1347,"line_start":48,"line_end":48,"column_start":17,"column_end":23},"name":"buffer","qualname":"buffer$187","value":"[u8; 6]","parent":null,"children":[],"decl_id":null,"docs":"","sig":null,"attributes":[]},{"kind":"Local","id":{"krate":0,"index":4294967103},"span":{"file_name":"src/main.rs","byte_start":1372,"byte_end":1376,"line_start":49,"line_end":49,"column_start":13,"column_end":17},"name":"byte","qualname":"byte$192","value":"&mut u8","parent":null,"children":[],"decl_id":null,"docs":"","sig":null,"attributes":[]},{"kind":"Local","id":{"krate":0,"index":4294967072},"span":{"file_name":"src/main.rs","byte_start":1646,"byte_end":1649,"line_start":56,"line_end":56,"column_start":13,"column_end":16},"name":"x_h","qualname":"x_h$223","value":"u16","parent":null,"children":[],"decl_id":null,"docs":"","sig":null,"attributes":[]},{"kind":"Local","id":{"krate":0,"index":4294967062},"span":{"file_name":"src/main.rs","byte_start":1686,"byte_end":1689,"line_start":57,"line_end":57,"column_start":13,"column_end":16},"name":"x_l","qualname":"x_l$233","value":"u16","parent":null,"children":[],"decl_id":null,"docs":"","sig":null,"attributes":[]},{"kind":"Local","id":{"krate":0,"index":4294967052},"span":{"file_name":"src/main.rs","byte_start":1726,"byte_end":1729,"line_start":58,"line_end":58,"column_start":13,"column_end":16},"name":"z_h","qualname":"z_h$243","value":"u16","parent":null,"children":[],"decl_id":null,"docs":"","sig":null,"attributes":[]},{"kind":"Local","id":{"krate":0,"index":4294967042},"span":{"file_name":"src/main.rs","byte_start":1766,"byte_end":1769,"line_start":59,"line_end":59,"column_start":13,"column_end":16},"name":"z_l","qualname":"z_l$253","value":"u16","parent":null,"children":[],"decl_id":null,"docs":"","sig":null,"attributes":[]},{"kind":"Local","id":{"krate":0,"index":4294967032},"span":{"file_name":"src/main.rs","byte_start":1806,"byte_end":1809,"line_start":60,"line_end":60,"column_start":13,"column_end":16},"name":"y_h","qualname":"y_h$263","value":"u16","parent":null,"children":[],"decl_id":null,"docs":"","sig":null,"attributes":[]},{"kind":"Local","id":{"krate":0,"index":4294967022},"span":{"file_name":"src/main.rs","byte_start":1846,"byte_end":1849,"line_start":61,"line_end":61,"column_start":13,"column_end":16},"name":"y_l","qualname":"y_l$273","value":"u16","parent":null,"children":[],"decl_id":null,"docs":"","sig":null,"attributes":[]},{"kind":"Local","id":{"krate":0,"index":4294967012},"span":{"file_name":"src/main.rs","byte_start":1887,"byte_end":1888,"line_start":63,"line_end":63,"column_start":13,"column_end":14},"name":"x","qualname":"x$283","value":"i16","parent":null,"children":[],"decl_id":null,"docs":"","sig":null,"attributes":[]},{"kind":"Local","id":{"krate":0,"index":4294967000},"span":{"file_name":"src/main.rs","byte_start":1930,"byte_end":1931,"line_start":64,"line_end":64,"column_start":13,"column_end":14},"name":"y","qualname":"y$295","value":"i16","parent":null,"children":[],"decl_id":null,"docs":"","sig":null,"attributes":[]},{"kind":"Local","id":{"krate":0,"index":4294966988},"span":{"file_name":"src/main.rs","byte_start":1973,"byte_end":1974,"line_start":65,"line_end":65,"column_start":13,"column_end":14},"name":"z","qualname":"z$307","value":"i16","parent":null,"children":[],"decl_id":null,"docs":"","sig":null,"attributes":[]}],"impls":[],"refs":[{"kind":"Mod","span":{"file_name":"src/main.rs","byte_start":75,"byte_end":80,"line_start":6,"line_end":6,"column_start":5,"column_end":10},"ref_id":{"krate":4,"index":0}},{"kind":"Mod","span":{"file_name":"src/main.rs","byte_start":75,"byte_end":80,"line_start":6,"line_end":6,"column_start":5,"column_end":10},"ref_id":{"krate":4,"index":0}},{"kind":"Mod","span":{"file_name":"src/main.rs","byte_start":75,"byte_end":80,"line_start":6,"line_end":6,"column_start":5,"column_end":10},"ref_id":{"krate":4,"index":0}},{"kind":"Mod","span":{"file_name":"src/main.rs","byte_start":75,"byte_end":80,"line_start":6,"line_end":6,"column_start":5,"column_end":10},"ref_id":{"krate":4,"index":0}},{"kind":"Mod","span":{"file_name":"src/main.rs","byte_start":108,"byte_end":115,"line_start":6,"line_end":6,"column_start":38,"column_end":45},"ref_id":{"krate":28,"index":150}},{"kind":"Function","span":{"file_name":"src/main.rs","byte_start":349,"byte_end":353,"line_start":17,"line_end":17,"column_start":45,"column_end":49},"ref_id":{"krate":4,"index":23}},{"kind":"Mod","span":{"file_name":"src/main.rs","byte_start":342,"byte_end":347,"line_start":17,"line_end":17,"column_start":38,"column_end":43},"ref_id":{"krate":4,"index":0}},{"kind":"Function","span":{"file_name":"src/main.rs","byte_start":489,"byte_end":494,"line_start":22,"line_end":22,"column_start":18,"column_end":23},"ref_id":{"krate":31,"index":81015}},{"kind":"Variable","span":{"file_name":"src/main.rs","byte_start":480,"byte_end":484,"line_start":22,"line_end":22,"column_start":9,"column_end":13},"ref_id":{"krate":0,"index":4294967239}},{"kind":"Variable","span":{"file_name":"src/main.rs","byte_start":485,"byte_end":488,"line_start":22,"line_end":22,"column_start":14,"column_end":17},"ref_id":{"krate":31,"index":80565}},{"kind":"Function","span":{"file_name":"src/main.rs","byte_start":523,"byte_end":530,"line_start":23,"line_end":23,"column_start":23,"column_end":30},"ref_id":{"krate":31,"index":81154}},{"kind":"Function","span":{"file_name":"src/main.rs","byte_start":515,"byte_end":520,"line_start":23,"line_end":23,"column_start":15,"column_end":20},"ref_id":{"krate":31,"index":81265}},{"kind":"Variable","span":{"file_name":"src/main.rs","byte_start":513,"byte_end":514,"line_start":23,"line_end":23,"column_start":13,"column_end":14},"ref_id":{"krate":0,"index":4294967226}},{"kind":"Function","span":{"file_name":"src/main.rs","byte_start":556,"byte_end":560,"line_start":24,"line_end":24,"column_start":23,"column_end":27},"ref_id":{"krate":31,"index":81202}},{"kind":"Function","span":{"file_name":"src/main.rs","byte_start":548,"byte_end":553,"line_start":24,"line_end":24,"column_start":15,"column_end":20},"ref_id":{"krate":31,"index":81270}},{"kind":"Variable","span":{"file_name":"src/main.rs","byte_start":546,"byte_end":547,"line_start":24,"line_end":24,"column_start":13,"column_end":14},"ref_id":{"krate":0,"index":4294967226}},{"kind":"Variable","span":{"file_name":"src/main.rs","byte_start":561,"byte_end":573,"line_start":24,"line_end":24,"column_start":28,"column_end":40},"ref_id":{"krate":0,"index":9}},{"kind":"Function","span":{"file_name":"src/main.rs","byte_start":599,"byte_end":608,"line_start":25,"line_end":25,"column_start":24,"column_end":33},"ref_id":{"krate":31,"index":81185}},{"kind":"Function","span":{"file_name":"src/main.rs","byte_start":590,"byte_end":596,"line_start":25,"line_end":25,"column_start":15,"column_end":21},"ref_id":{"krate":31,"index":81268}},{"kind":"Variable","span":{"file_name":"src/main.rs","byte_start":588,"byte_end":589,"line_start":25,"line_end":25,"column_start":13,"column_end":14},"ref_id":{"krate":0,"index":4294967226}},{"kind":"Function","span":{"file_name":"src/main.rs","byte_start":635,"byte_end":639,"line_start":26,"line_end":26,"column_start":24,"column_end":28},"ref_id":{"krate":31,"index":81126}},{"kind":"Function","span":{"file_name":"src/main.rs","byte_start":626,"byte_end":632,"line_start":26,"line_end":26,"column_start":15,"column_end":21},"ref_id":{"krate":31,"index":81262}},{"kind":"Variable","span":{"file_name":"src/main.rs","byte_start":624,"byte_end":625,"line_start":26,"line_end":26,"column_start":13,"column_end":14},"ref_id":{"krate":0,"index":4294967226}},{"kind":"Function","span":{"file_name":"src/main.rs","byte_start":668,"byte_end":677,"line_start":27,"line_end":27,"column_start":25,"column_end":34},"ref_id":{"krate":31,"index":81107}},{"kind":"Function","span":{"file_name":"src/main.rs","byte_start":658,"byte_end":665,"line_start":27,"line_end":27,"column_start":15,"column_end":22},"ref_id":{"krate":31,"index":81260}},{"kind":"Variable","span":{"file_name":"src/main.rs","byte_start":656,"byte_end":657,"line_start":27,"line_end":27,"column_start":13,"column_end":14},"ref_id":{"krate":0,"index":4294967226}},{"kind":"Function","span":{"file_name":"src/main.rs","byte_start":774,"byte_end":786,"line_start":31,"line_end":31,"column_start":38,"column_end":50},"ref_id":{"krate":31,"index":81780}},{"kind":"Function","span":{"file_name":"src/main.rs","byte_start":767,"byte_end":771,"line_start":31,"line_end":31,"column_start":31,"column_end":35},"ref_id":{"krate":31,"index":81855}},{"kind":"Function","span":{"file_name":"src/main.rs","byte_start":760,"byte_end":764,"line_start":31,"line_end":31,"column_start":24,"column_end":28},"ref_id":{"krate":31,"index":81683}},{"kind":"Variable","span":{"file_name":"src/main.rs","byte_start":751,"byte_end":755,"line_start":31,"line_end":31,"column_start":15,"column_end":19},"ref_id":{"krate":0,"index":4294967239}},{"kind":"Variable","span":{"file_name":"src/main.rs","byte_start":756,"byte_end":759,"line_start":31,"line_end":31,"column_start":20,"column_end":23},"ref_id":{"krate":31,"index":80570}},{"kind":"Function","span":{"file_name":"src/main.rs","byte_start":887,"byte_end":892,"line_start":34,"line_end":34,"column_start":19,"column_end":24},"ref_id":{"krate":31,"index":82020}},{"kind":"Variable","span":{"file_name":"src/main.rs","byte_start":877,"byte_end":881,"line_start":34,"line_end":34,"column_start":9,"column_end":13},"ref_id":{"krate":0,"index":4294967239}},{"kind":"Variable","span":{"file_name":"src/main.rs","byte_start":882,"byte_end":886,"line_start":34,"line_end":34,"column_start":14,"column_end":18},"ref_id":{"krate":31,"index":80574}},{"kind":"Function","span":{"file_name":"src/main.rs","byte_start":908,"byte_end":912,"line_start":34,"line_end":34,"column_start":40,"column_end":44},"ref_id":{"krate":31,"index":82033}},{"kind":"Function","span":{"file_name":"src/main.rs","byte_start":899,"byte_end":905,"line_start":34,"line_end":34,"column_start":31,"column_end":37},"ref_id":{"krate":31,"index":82044}},{"kind":"Variable","span":{"file_name":"src/main.rs","byte_start":897,"byte_end":898,"line_start":34,"line_end":34,"column_start":29,"column_end":30},"ref_id":{"krate":0,"index":4294967171}},{"kind":"Variable","span":{"file_name":"src/main.rs","byte_start":913,"byte_end":922,"line_start":34,"line_end":34,"column_start":45,"column_end":54},"ref_id":{"krate":0,"index":10}},{"kind":"Function","span":{"file_name":"src/main.rs","byte_start":1023,"byte_end":1035,"line_start":37,"line_end":37,"column_start":36,"column_end":48},"ref_id":{"krate":31,"index":81750}},{"kind":"Function","span":{"file_name":"src/main.rs","byte_start":1018,"byte_end":1020,"line_start":37,"line_end":37,"column_start":31,"column_end":33},"ref_id":{"krate":31,"index":81840}},{"kind":"Function","span":{"file_name":"src/main.rs","byte_start":1011,"byte_end":1015,"line_start":37,"line_end":37,"column_start":24,"column_end":28},"ref_id":{"krate":31,"index":81683}},{"kind":"Variable","span":{"file_name":"src/main.rs","byte_start":1002,"byte_end":1006,"line_start":37,"line_end":37,"column_start":15,"column_end":19},"ref_id":{"krate":0,"index":4294967239}},{"kind":"Variable","span":{"file_name":"src/main.rs","byte_start":1007,"byte_end":1010,"line_start":37,"line_end":37,"column_start":20,"column_end":23},"ref_id":{"krate":31,"index":80570}},{"kind":"Function","span":{"file_name":"src/main.rs","byte_start":1163,"byte_end":1169,"line_start":41,"line_end":41,"column_start":18,"column_end":24},"ref_id":{"krate":31,"index":81011}},{"kind":"Variable","span":{"file_name":"src/main.rs","byte_start":1154,"byte_end":1158,"line_start":41,"line_end":41,"column_start":9,"column_end":13},"ref_id":{"krate":0,"index":4294967239}},{"kind":"Variable","span":{"file_name":"src/main.rs","byte_start":1159,"byte_end":1162,"line_start":41,"line_end":41,"column_start":14,"column_end":17},"ref_id":{"krate":31,"index":80565}},{"kind":"Function","span":{"file_name":"src/main.rs","byte_start":1201,"byte_end":1208,"line_start":42,"line_end":42,"column_start":23,"column_end":30},"ref_id":{"krate":31,"index":81154}},{"kind":"Function","span":{"file_name":"src/main.rs","byte_start":1193,"byte_end":1198,"line_start":42,"line_end":42,"column_start":15,"column_end":20},"ref_id":{"krate":31,"index":81265}},{"kind":"Variable","span":{"file_name":"src/main.rs","byte_start":1191,"byte_end":1192,"line_start":42,"line_end":42,"column_start":13,"column_end":14},"ref_id":{"krate":0,"index":4294967140}},{"kind":"Function","span":{"file_name":"src/main.rs","byte_start":1235,"byte_end":1239,"line_start":43,"line_end":43,"column_start":24,"column_end":28},"ref_id":{"krate":31,"index":81126}},{"kind":"Function","span":{"file_name":"src/main.rs","byte_start":1226,"byte_end":1232,"line_start":43,"line_end":43,"column_start":15,"column_end":21},"ref_id":{"krate":31,"index":81262}},{"kind":"Variable","span":{"file_name":"src/main.rs","byte_start":1224,"byte_end":1225,"line_start":43,"line_end":43,"column_start":13,"column_end":14},"ref_id":{"krate":0,"index":4294967140}},{"kind":"Function","span":{"file_name":"src/main.rs","byte_start":1267,"byte_end":1274,"line_start":44,"line_end":44,"column_start":24,"column_end":31},"ref_id":{"krate":31,"index":81184}},{"kind":"Function","span":{"file_name":"src/main.rs","byte_start":1258,"byte_end":1264,"line_start":44,"line_end":44,"column_start":15,"column_end":21},"ref_id":{"krate":31,"index":81268}},{"kind":"Variable","span":{"file_name":"src/main.rs","byte_start":1256,"byte_end":1257,"line_start":44,"line_end":44,"column_start":13,"column_end":14},"ref_id":{"krate":0,"index":4294967140}},{"kind":"Function","span":{"file_name":"src/main.rs","byte_start":1302,"byte_end":1309,"line_start":45,"line_end":45,"column_start":25,"column_end":32},"ref_id":{"krate":31,"index":81106}},{"kind":"Function","span":{"file_name":"src/main.rs","byte_start":1292,"byte_end":1299,"line_start":45,"line_end":45,"column_start":15,"column_end":22},"ref_id":{"krate":31,"index":81260}},{"kind":"Variable","span":{"file_name":"src/main.rs","byte_start":1290,"byte_end":1291,"line_start":45,"line_end":45,"column_start":13,"column_end":14},"ref_id":{"krate":0,"index":4294967140}},{"kind":"Variable","span":{"file_name":"src/main.rs","byte_start":1385,"byte_end":1391,"line_start":49,"line_end":49,"column_start":26,"column_end":32},"ref_id":{"krate":0,"index":4294967108}},{"kind":"Function","span":{"file_name":"src/main.rs","byte_start":1488,"byte_end":1500,"line_start":51,"line_end":51,"column_start":42,"column_end":54},"ref_id":{"krate":31,"index":81774}},{"kind":"Function","span":{"file_name":"src/main.rs","byte_start":1481,"byte_end":1485,"line_start":51,"line_end":51,"column_start":35,"column_end":39},"ref_id":{"krate":31,"index":81852}},{"kind":"Function","span":{"file_name":"src/main.rs","byte_start":1474,"byte_end":1478,"line_start":51,"line_end":51,"column_start":28,"column_end":32},"ref_id":{"krate":31,"index":81683}},{"kind":"Variable","span":{"file_name":"src/main.rs","byte_start":1465,"byte_end":1469,"line_start":51,"line_end":51,"column_start":19,"column_end":23},"ref_id":{"krate":0,"index":4294967239}},{"kind":"Variable","span":{"file_name":"src/main.rs","byte_start":1470,"byte_end":1473,"line_start":51,"line_end":51,"column_start":24,"column_end":27},"ref_id":{"krate":31,"index":80570}},{"kind":"Variable","span":{"file_name":"src/main.rs","byte_start":1520,"byte_end":1524,"line_start":53,"line_end":53,"column_start":14,"column_end":18},"ref_id":{"krate":0,"index":4294967103}},{"kind":"Function","span":{"file_name":"src/main.rs","byte_start":1553,"byte_end":1557,"line_start":53,"line_end":53,"column_start":47,"column_end":51},"ref_id":{"krate":31,"index":82002}},{"kind":"Function","span":{"file_name":"src/main.rs","byte_start":1544,"byte_end":1550,"line_start":53,"line_end":53,"column_start":38,"column_end":44},"ref_id":{"krate":31,"index":82005}},{"kind":"Function","span":{"file_name":"src/main.rs","byte_start":1537,"byte_end":1541,"line_start":53,"line_end":53,"column_start":31,"column_end":35},"ref_id":{"krate":31,"index":81998}},{"kind":"Variable","span":{"file_name":"src/main.rs","byte_start":1527,"byte_end":1531,"line_start":53,"line_end":53,"column_start":21,"column_end":25},"ref_id":{"krate":0,"index":4294967239}},{"kind":"Variable","span":{"file_name":"src/main.rs","byte_start":1532,"byte_end":1536,"line_start":53,"line_end":53,"column_start":26,"column_end":30},"ref_id":{"krate":31,"index":80573}},{"kind":"Function","span":{"file_name":"src/main.rs","byte_start":1657,"byte_end":1661,"line_start":56,"line_end":56,"column_start":24,"column_end":28},"ref_id":{"krate":1,"index":1827}},{"kind":"Variable","span":{"file_name":"src/main.rs","byte_start":1662,"byte_end":1668,"line_start":56,"line_end":56,"column_start":29,"column_end":35},"ref_id":{"krate":0,"index":4294967108}},{"kind":"Function","span":{"file_name":"src/main.rs","byte_start":1697,"byte_end":1701,"line_start":57,"line_end":57,"column_start":24,"column_end":28},"ref_id":{"krate":1,"index":1827}},{"kind":"Variable","span":{"file_name":"src/main.rs","byte_start":1702,"byte_end":1708,"line_start":57,"line_end":57,"column_start":29,"column_end":35},"ref_id":{"krate":0,"index":4294967108}},{"kind":"Function","span":{"file_name":"src/main.rs","byte_start":1737,"byte_end":1741,"line_start":58,"line_end":58,"column_start":24,"column_end":28},"ref_id":{"krate":1,"index":1827}},{"kind":"Variable","span":{"file_name":"src/main.rs","byte_start":1742,"byte_end":1748,"line_start":58,"line_end":58,"column_start":29,"column_end":35},"ref_id":{"krate":0,"index":4294967108}},{"kind":"Function","span":{"file_name":"src/main.rs","byte_start":1777,"byte_end":1781,"line_start":59,"line_end":59,"column_start":24,"column_end":28},"ref_id":{"krate":1,"index":1827}},{"kind":"Variable","span":{"file_name":"src/main.rs","byte_start":1782,"byte_end":1788,"line_start":59,"line_end":59,"column_start":29,"column_end":35},"ref_id":{"krate":0,"index":4294967108}},{"kind":"Function","span":{"file_name":"src/main.rs","byte_start":1817,"byte_end":1821,"line_start":60,"line_end":60,"column_start":24,"column_end":28},"ref_id":{"krate":1,"index":1827}},{"kind":"Variable","span":{"file_name":"src/main.rs","byte_start":1822,"byte_end":1828,"line_start":60,"line_end":60,"column_start":29,"column_end":35},"ref_id":{"krate":0,"index":4294967108}},{"kind":"Function","span":{"file_name":"src/main.rs","byte_start":1857,"byte_end":1861,"line_start":61,"line_end":61,"column_start":24,"column_end":28},"ref_id":{"krate":1,"index":1827}},{"kind":"Variable","span":{"file_name":"src/main.rs","byte_start":1862,"byte_end":1868,"line_start":61,"line_end":61,"column_start":29,"column_end":35},"ref_id":{"krate":0,"index":4294967108}},{"kind":"Variable","span":{"file_name":"src/main.rs","byte_start":1893,"byte_end":1896,"line_start":63,"line_end":63,"column_start":19,"column_end":22},"ref_id":{"krate":0,"index":4294967072}},{"kind":"Variable","span":{"file_name":"src/main.rs","byte_start":1905,"byte_end":1908,"line_start":63,"line_end":63,"column_start":31,"column_end":34},"ref_id":{"krate":0,"index":4294967062}},{"kind":"Variable","span":{"file_name":"src/main.rs","byte_start":1936,"byte_end":1939,"line_start":64,"line_end":64,"column_start":19,"column_end":22},"ref_id":{"krate":0,"index":4294967032}},{"kind":"Variable","span":{"file_name":"src/main.rs","byte_start":1948,"byte_end":1951,"line_start":64,"line_end":64,"column_start":31,"column_end":34},"ref_id":{"krate":0,"index":4294967022}},{"kind":"Variable","span":{"file_name":"src/main.rs","byte_start":1979,"byte_end":1982,"line_start":65,"line_end":65,"column_start":19,"column_end":22},"ref_id":{"krate":0,"index":4294967052}},{"kind":"Variable","span":{"file_name":"src/main.rs","byte_start":1991,"byte_end":1994,"line_start":65,"line_end":65,"column_start":31,"column_end":34},"ref_id":{"krate":0,"index":4294967042}},{"kind":"Variable","span":{"file_name":"src/main.rs","byte_start":2141,"byte_end":2144,"line_start":69,"line_end":69,"column_start":20,"column_end":23},"ref_id":{"krate":0,"index":4294967237}},{"kind":"Variable","span":{"file_name":"src/main.rs","byte_start":2145,"byte_end":2149,"line_start":69,"line_end":69,"column_start":24,"column_end":28},"ref_id":{"krate":6,"index":229}},{"kind":"Variable","span":{"file_name":"src/main.rs","byte_start":2163,"byte_end":2164,"line_start":69,"line_end":69,"column_start":42,"column_end":43},"ref_id":{"krate":0,"index":4294967012}},{"kind":"Variable","span":{"file_name":"src/main.rs","byte_start":2165,"byte_end":2166,"line_start":69,"line_end":69,"column_start":44,"column_end":45},"ref_id":{"krate":0,"index":4294967000}},{"kind":"Variable","span":{"file_name":"src/main.rs","byte_start":2167,"byte_end":2168,"line_start":69,"line_end":69,"column_start":46,"column_end":47},"ref_id":{"krate":0,"index":4294966988}},{"kind":"Function","span":{"file_name":"src/main.rs","byte_start":2243,"byte_end":2251,"line_start":73,"line_end":73,"column_start":15,"column_end":23},"ref_id":{"krate":21,"index":11}},{"kind":"Variable","span":{"file_name":"src/main.rs","byte_start":2237,"byte_end":2242,"line_start":73,"line_end":73,"column_start":9,"column_end":14},"ref_id":{"krate":0,"index":4294967238}}],"macro_refs":[],"relations":[]}